amsc/__init__.py
amsc/foo.py
amsc-0.0.1.dist-info/METADATA
amsc-0.0.1.dist-info/WHEEL
amsc-0.0.1.dist-info/RECORD
