Metadata-Version: 2.4
Name: amsc
Version: 0.0.1
Summary: American Science Cloud
Project-URL: Homepage, https://saforem2.github.io/amsc/
Project-URL: Repository, https://github.com/saforem2/amsc
Project-URL: Documentation, https://saforem2.github.io/amsc/
Author-email: Sam Foreman <saforem2@gmail.com>
Keywords: python
Classifier: Intended Audience :: Developers
Classifier: Programming Language :: Python
Classifier: Programming Language :: Python :: 3
Classifier: Programming Language :: Python :: 3.10
Classifier: Programming Language :: Python :: 3.11
Classifier: Programming Language :: Python :: 3.12
Classifier: Programming Language :: Python :: 3.13
Classifier: Programming Language :: Python :: 3.14
Classifier: Topic :: Software Development :: Libraries :: Python Modules
Requires-Python: <4.0,>=3.10
